teslapy/__init__.py
teslapy/endpoints.json
teslapy/option_codes.json
TeslaPy-2.9.0.dist-info/LICENSE
TeslaPy-2.9.0.dist-info/METADATA
TeslaPy-2.9.0.dist-info/WHEEL
TeslaPy-2.9.0.dist-info/top_level.txt
TeslaPy-2.9.0.dist-info/RECORD
