Metadata-Version: 2.1
Name: TeslaPy
Version: 2.9.0
Summary: A Python module to use the Tesla Motors Owner API
Home-page: https://github.com/tdorssers/TeslaPy
Author: Tim Dorssers
Author-email: tim.dorssers@xs4all.nl
Classifier: License :: OSI Approved :: MIT License
Classifier: Programming Language :: Python :: 2
Classifier: Programming Language :: Python :: 2.7
Classifier: Programming Language :: Python :: 3
Classifier: Programming Language :: Python :: 3.5
Classifier: Programming Language :: Python :: 3.6
Classifier: Programming Language :: Python :: 3.7
Classifier: Programming Language :: Python :: 3.8
Classifier: Programming Language :: Python :: 3.9
Classifier: Programming Language :: Python :: 3.10
Classifier: Programming Language :: Python :: 3.11
Classifier: Operating System :: OS Independent
License-File: LICENSE
Requires-Dist: requests>=2.4.2
Requires-Dist: requests_oauthlib
Requires-Dist: websocket-client>=0.59.0
